mario_airflow_utils/__init__.py
mario_airflow_utils/mario_airflow_utils.py
mario_airflow_utils-0.7.0.dist-info/LICENSE
mario_airflow_utils-0.7.0.dist-info/METADATA
mario_airflow_utils-0.7.0.dist-info/WHEEL
mario_airflow_utils-0.7.0.dist-info/entry_points.txt
mario_airflow_utils-0.7.0.dist-info/top_level.txt
mario_airflow_utils-0.7.0.dist-info/RECORD
