Metadata-Version: 2.1
Name: mario-airflow-utils
Version: 0.7.0
Summary: apache airflow utils
Home-page: https://dMario24.github.io/mario_airflow_utils
Author: dMario24
Author-email: data.mario24@gmail.com
License: GNU General Public License (GPL)
Project-URL: Bug Tracker, https://github.com/dMario24/mario_airflow_utils/issues
Platform: macOS
Classifier: Programming Language :: Python :: 3
Classifier: License :: OSI Approved :: GNU General Public License (GPL)
Classifier: Operating System :: OS Independent
Requires-Python: >=3.6
License-File: LICENSE
